graph_ensembles/__init__.py
graph_ensembles/graphs.py
graph_ensembles/lib.py
graph_ensembles/models.py
graph_ensembles/solver.py
graph_ensembles/spark/__init__.py
graph_ensembles/spark/models.py
graph_ensembles/sparse/__init__.py
graph_ensembles/sparse/graphs.py
graph_ensembles/sparse/models/__init__.py
graph_ensembles/sparse/models/conditional.py
graph_ensembles/sparse/models/ensembles.py
graph_ensembles/sparse/models/fitness.py
graph_ensembles/sparse/models/invariant.py
graph_ensembles/sparse/models/random.py
graph_ensembles-0.3.5.dist-info/LICENSE.txt
graph_ensembles-0.3.5.dist-info/METADATA
graph_ensembles-0.3.5.dist-info/WHEEL
graph_ensembles-0.3.5.dist-info/top_level.txt
graph_ensembles-0.3.5.dist-info/RECORD
