Metadata-Version: 2.1
Name: graph-ensembles
Version: 0.3.5
Summary: The graph ensemble package contains a set of methods to build fitness based graph ensembles from marginal information.
Home-page: https://github.com/LeonardoIalongo/graph-ensembles
Author: Leonardo Niccolò Ialongo
Author-email: leonardo.ialongo@gmail.com
License: GNU General Public License v3
Classifier: Development Status :: 2 - Pre-Alpha
Classifier: License :: OSI Approved :: GNU General Public License v3 (GPLv3)
Classifier: Natural Language :: English
Classifier: Programming Language :: Python :: 3
Classifier: Programming Language :: Python :: 3.7
Classifier: Programming Language :: Python :: 3.8
Classifier: Programming Language :: Python :: 3.9
Classifier: Operating System :: OS Independent
Requires-Python: >=3.0
License-File: LICENSE.txt
Requires-Dist: numpy >=1.22
Requires-Dist: numba >=0.56
Requires-Dist: scipy >=1.9
Requires-Dist: pandas >=1.1
Requires-Dist: networkx >=3.0
